__init__.py
mod_docx.py
mod_docx-0.1.0.dist-info/LICENSE
mod_docx-0.1.0.dist-info/METADATA
mod_docx-0.1.0.dist-info/WHEEL
mod_docx-0.1.0.dist-info/top_level.txt
mod_docx-0.1.0.dist-info/RECORD
